embbedFirmata/__init__.py
embbedFirmata/embffload.py
embbedfirmata-0.1.1.dist-info/METADATA
embbedfirmata-0.1.1.dist-info/WHEEL
embbedfirmata-0.1.1.dist-info/entry_points.txt
embbedfirmata-0.1.1.dist-info/top_level.txt
embbedfirmata-0.1.1.dist-info/RECORD
