Metadata-Version: 2.4
Name: embbedFirmata
Version: 0.1.1
Summary: Crontol a embbbed system via firmata.
Author: Jhonata Rios Carneiro
Requires-Python: >=3.8
Requires-Dist: pyserial==3.5
